<?xml version="1.0" encoding="UTF-8"?>
<ofd:Page xmlns:ofd="http://www.ofdspec.org/2016"><ofd:Area><ofd:PhysicalBox>0 0 209.9998 296.9948</ofd:PhysicalBox><ofd:CropBox>0 0 209.9998 296.9948</ofd:CropBox></ofd:Area><ofd:Content><ofd:Layer ID="2"><ofd:ImageObject ID="4" CTM="30.0038 0 0 30.0038 0 0" Boundary="135.9165 63.3412 30.0038 30.0037" ResourceID="3"/><ofd:ImageObject ID="5" CTM="30.0038 0 0 30.0038 0 0" Boundary="135.9165 63.3412 30.0038 30.0037" ResourceID="3"/><ofd:TextObject ID="7" CTM="0.3528 0 0 0.3528 0 0" Boundary="141.6579 79.955 18.8881 3.1718" Font="6" Size="9"><ofd:FillColor Value="255 0 0"/><ofd:CGTransform CodePosition="0" CodeCount="6" GlyphCount="6"><ofd:Glyphs>68 46 39 79 101 143</ofd:Glyphs></ofd:CGTransform><ofd:TextCode X="0" Y="7.731" DeltaX="9 9 9 9 9">北京上地支行</ofd:TextCode></ofd:TextObject><ofd:TextObject ID="8" CTM="0.3528 0 0 0.3528 0 0" Boundary="141.6579 86.0404 18.9166 3.1718" LineWidth="0.36" Font="6" Size="9" Stroke="true"><ofd:FillColor Value="255 0 0"/><ofd:StrokeColor Value="255 0 0"/><ofd:CGTransform CodePosition="0" CodeCount="12" GlyphCount="12"><ofd:Glyphs>29 23 28 26 19 30 7 10 15 10 6 8</ofd:Glyphs></ofd:CGTransform><ofd:TextCode X="0" Y="7.731" DeltaX="4.5 4.5 4.5 4.5 4.5 4.5 4.5 4.5 4.5 4.5 4.5">YOXUGZ149402</ofd:TextCode></ofd:TextObject><ofd:TextObject ID="9" CTM="0.3528 0 0 0.3528 0 0" Boundary="8.6651 88.1861 137.6754 2.815" Font="6" Size="7.9875"><ofd:CGTransform CodePosition="0" CodeCount="56" GlyphCount="56"><ofd:Glyphs>118 77 70 49 87 96 128 86 45 108 44 53 100 173 73 159 157 91 143 139 134 2 35 35 35 5 32 32 31 5 32 34 33 3 116 167 128 51 37 126 84 77 70 73 160 81 97 72 173 147 67 160 81 144 149 37</ofd:Glyphs></ofd:CGTransform><ofd:TextCode X="0" Y="6.8613" DeltaX="7.9875 7.9875 7.9875 7.9875 7.9875 7.9875 7.9875 7.9875 7.9875 7.9875 7.9875 7.9875 7.9875 7.9875 7.9875 7.9875 7.9875 7.9875 7.9875 7.9875 7.9875 3.9937 3.9937 3.9937 3.9937 3.9937 3.9937 3.9937 3.9937 3.9937 3.9937 3.9937 3.9937 3.9937 7.9875 7.9875 7.9875 7.9875 7.9875 7.9875 7.9875 7.9875 7.9875 7.9875 7.9875 7.9875 7.9875 7.9875 7.9875 7.9875 7.9875 7.9875 7.9875 7.9875 7.9875">此回单以客户真实交易为依据，可通过建行网站(www.ccb.com)校验真伪。电子回单可重复打印，请勿重复记账。</ofd:TextCode></ofd:TextObject><ofd:PathObject ID="10" CTM="0.3528 0 0 0.3528 0 0" Boundary="8.2682 20.5317 7.2231 0.2646" Stroke="false" Fill="true"><ofd:FillColor Value="0 0 0"/><ofd:Clips TransFlag="false"><ofd:Clip><ofd:Area CTM="0.3528 0 0 0.3528 0 0"><ofd:Path Boundary="0.375 -58.2 547.65 841.8375" Stroke="false" Fill="true"><ofd:AbbreviatedData>M 0 0 L 547.65 0 L 547.65 841.8375 L 0 841.8375 C </ofd:AbbreviatedData></ofd:Path></ofd:Area></ofd:Clip></ofd:Clips><ofd:AbbreviatedData>M 0 0 L 20.475 0 L 19.725 0.7499 L 0.75 0.7499 C </ofd:AbbreviatedData></ofd:PathObject><ofd:PathObject ID="12" CTM="0.3528 0 0 0.3528 0 0" Boundary="15.2268 20.5317 0.2646 14.8299" Stroke="false" Fill="true"><ofd:FillColor Value="0 0 0"/><ofd:AbbreviatedData>M 0.75 0 L 0.75 42.0375 L 0 41.2875 L 0 0.7499 C </ofd:AbbreviatedData></ofd:PathObject><ofd:PathObject ID="13" CTM="0.3528 0 0 0.3528 0 0" Boundary="8.2682 35.097 7.2231 0.2646" Stroke="false" Fill="true"><ofd:FillColor Value="0 0 0"/><ofd:Clips TransFlag="false"><ofd:Clip><ofd:Area CTM="0.3528 0 0 0.3528 0 0"><ofd:Path Boundary="0.375 -99.4875 547.65 841.8375" Stroke="false" Fill="true"><ofd:AbbreviatedData>M 0 0 L 547.65 0 L 547.65 841.8375 L 0 841.8375 C </ofd:AbbreviatedData></ofd:Path></ofd:Area></ofd:Clip></ofd:Clips><ofd:AbbreviatedData>M 20.475 0.75 L 0 0.75 L 0.75 0 L 19.725 0 C </ofd:AbbreviatedData></ofd:PathObject><ofd:PathObject ID="15" CTM="0.3528 0 0 0.3528 0 0" Boundary="8.2682 20.5317 0.2646 14.8299" Stroke="false" Fill="true"><ofd:FillColor Value="0 0 0"/><ofd:Clips TransFlag="false"><ofd:Clip><ofd:Area CTM="0.3528 0 0 0.3528 0 0"><ofd:Path Boundary="0.375 -58.2 547.65 841.8375" Stroke="false" Fill="true"><ofd:AbbreviatedData>M 0 0 L 547.65 0 L 547.65 841.8375 L 0 841.8375 C </ofd:AbbreviatedData></ofd:Path></ofd:Area></ofd:Clip></ofd:Clips><ofd:AbbreviatedData>M 0 42.0375 L 0 0 L 0.75 0.7499 L 0.75 41.2875 C </ofd:AbbreviatedData></ofd:PathObject><ofd:PathObject ID="17" CTM="0.3528 0 0 0.3528 0 0" Boundary="15.2268 20.5317 16.6026 0.2646" Stroke="false" Fill="true"><ofd:FillColor Value="0 0 0"/><ofd:AbbreviatedData>M 0 0 L 47.0625 0 L 46.3125 0.7499 L 0.75 0.7499 C </ofd:AbbreviatedData></ofd:PathObject><ofd:PathObject ID="18" CTM="0.3528 0 0 0.3528 0 0" Boundary="31.5648 20.5317 0.2646 5.1197" Stroke="false" Fill="true"><ofd:FillColor Value="0 0 0"/><ofd:AbbreviatedData>M 0.75 0 L 0.75 14.5125 L 0 13.7625 L 0 0.7499 C </ofd:AbbreviatedData></ofd:PathObject><ofd:PathObject ID="19" CTM="0.3528 0 0 0.3528 0 0" Boundary="15.2268 25.3868 16.6026 0.2646" Stroke="false" Fill="true"><ofd:FillColor Value="0 0 0"/><ofd:AbbreviatedData>M 47.0625 0.7501 L 0 0.7501 L 0.75 0 L 46.3125 0 C </ofd:AbbreviatedData></ofd:PathObject><ofd:PathObject ID="20" CTM="0.3528 0 0 0.3528 0 0" Boundary="15.2268 20.5317 0.2646 5.1197" Stroke="false" Fill="true"><ofd:FillColor Value="0 0 0"/><ofd:AbbreviatedData>M 0 14.5125 L 0 0 L 0.75 0.7499 L 0.75 13.7625 C </ofd:AbbreviatedData></ofd:PathObject><ofd:PathObject ID="21" CTM="0.3528 0 0 0.3528 0 0" Boundary="31.5648 20.5317 67.1909 0.2646" Stroke="false" Fill="true"><ofd:FillColor Value="0 0 0"/><ofd:AbbreviatedData>M 0 0 L 190.4625 0 L 189.7125 0.7499 L 0.75 0.7499 C </ofd:AbbreviatedData></ofd:PathObject><ofd:PathObject ID="22" CTM="0.3528 0 0 0.3528 0 0" Boundary="98.4911 20.5317 0.2646 5.1197" Stroke="false" Fill="true"><ofd:FillColor Value="0 0 0"/><ofd:AbbreviatedData>M 0.75 0 L 0.75 14.5125 L 0 13.7625 L 0 0.7499 C </ofd:AbbreviatedData></ofd:PathObject><ofd:PathObject ID="23" CTM="0.3528 0 0 0.3528 0 0" Boundary="31.5648 25.3868 67.1909 0.2646" Stroke="false" Fill="true"><ofd:FillColor Value="0 0 0"/><ofd:AbbreviatedData>M 190.4625 0.7501 L 0 0.7501 L 0.75 0 L 189.7125 0 C </ofd:AbbreviatedData></ofd:PathObject><ofd:PathObject ID="24" CTM="0.3528 0 0 0.3528 0 0" Boundary="31.5648 20.5317 0.2646 5.1197" Stroke="false" Fill="true"><ofd:FillColor Value="0 0 0"/><ofd:AbbreviatedData>M 0 14.5125 L 0 0 L 0.75 0.7499 L 0.75 13.7625 C </ofd:AbbreviatedData></ofd:PathObject><ofd:PathObject ID="25" CTM="0.3528 0 0 0.3528 0 0" Boundary="98.4911 20.5317 7.2231 0.2646" Stroke="false" Fill="true"><ofd:FillColor Value="0 0 0"/><ofd:AbbreviatedData>M 0 0 L 20.475 0 L 19.725 0.7499 L 0.75 0.7499 C </ofd:AbbreviatedData></ofd:PathObject><ofd:PathObject ID="26" CTM="0.3528 0 0 0.3528 0 0" Boundary="105.4497 20.5317 0.2646 14.8299" Stroke="false" Fill="true"><ofd:FillColor Value="0 0 0"/><ofd:AbbreviatedData>M 0.75 0 L 0.75 42.0375 L 0 41.2875 L 0 0.7499 C </ofd:AbbreviatedData></ofd:PathObject><ofd:PathObject ID="27" CTM="0.3528 0 0 0.3528 0 0" Boundary="98.4911 35.097 7.2231 0.2646" Stroke="false" Fill="true"><ofd:FillColor Value="0 0 0"/><ofd:AbbreviatedData>M 20.475 0.75 L 0 0.75 L 0.75 0 L 19.725 0 C </ofd:AbbreviatedData></ofd:PathObject><ofd:PathObject ID="28" CTM="0.3528 0 0 0.3528 0 0" Boundary="98.4911 20.5317 0.2646 14.8299" Stroke="false" Fill="true"><ofd:FillColor Value="0 0 0"/><ofd:AbbreviatedData>M 0 42.0375 L 0 0 L 0.75 0.7499 L 0.75 41.2875 C </ofd:AbbreviatedData></ofd:PathObject><ofd:PathObject ID="29" CTM="0.3528 0 0 0.3528 0 0" Boundary="105.4497 20.5317 16.6026 0.2646" Stroke="false" Fill="true"><ofd:FillColor Value="0 0 0"/><ofd:AbbreviatedData>M 0 0 L 47.0625 0 L 46.3125 0.7499 L 0.75 0.7499 C </ofd:AbbreviatedData></ofd:PathObject><ofd:PathObject ID="30" CTM="0.3528 0 0 0.3528 0 0" Boundary="121.7877 20.5317 0.2646 5.1197" Stroke="false" Fill="true"><ofd:FillColor Value="0 0 0"/><ofd:AbbreviatedData>M 0.75 0 L 0.75 14.5125 L 0 13.7625 L 0 0.7499 C </ofd:AbbreviatedData></ofd:PathObject><ofd:PathObject ID="31" CTM="0.3528 0 0 0.3528 0 0" Boundary="105.4497 25.3868 16.6026 0.2646" Stroke="false" Fill="true"><ofd:FillColor Value="0 0 0"/><ofd:AbbreviatedData>M 47.0625 0.7501 L 0 0.7501 L 0.75 0 L 46.3125 0 C </ofd:AbbreviatedData></ofd:PathObject><ofd:PathObject ID="32" CTM="0.3528 0 0 0.3528 0 0" Boundary="105.4497 20.5317 0.2646 5.1197" Stroke="false" Fill="true"><ofd:FillColor Value="0 0 0"/><ofd:AbbreviatedData>M 0 14.5125 L 0 0 L 0.75 0.7499 L 0.75 13.7625 C </ofd:AbbreviatedData></ofd:PathObject><ofd:PathObject ID="33" CTM="0.3528 0 0 0.3528 0 0" Boundary="121.7877 20.5317 67.1909 0.2646" Stroke="false" Fill="true"><ofd:FillColor Value="0 0 0"/><ofd:AbbreviatedData>M 0 0 L 190.4625 0 L 189.7126 0.7499 L 0.75 0.7499 C </ofd:AbbreviatedData></ofd:PathObject><ofd:PathObject ID="34" CTM="0.3528 0 0 0.3528 0 0" Boundary="188.7141 20.5317 0.2646 5.1197" Stroke="false" Fill="true"><ofd:FillColor Value="0 0 0"/><ofd:AbbreviatedData>M 0.7499 0 L 0.7499 14.5125 L 0 13.7625 L 0 0.7499 C </ofd:AbbreviatedData></ofd:PathObject><ofd:PathObject ID="35" CTM="0.3528 0 0 0.3528 0 0" Boundary="121.7877 25.3868 67.1909 0.2646" Stroke="false" Fill="true"><ofd:FillColor Value="0 0 0"/><ofd:AbbreviatedData>M 190.4625 0.7501 L 0 0.7501 L 0.75 0 L 189.7126 0 C </ofd:AbbreviatedData></ofd:PathObject><ofd:PathObject ID="36" CTM="0.3528 0 0 0.3528 0 0" Boundary="121.7877 20.5317 0.2646 5.1197" Stroke="false" Fill="true"><ofd:FillColor Value="0 0 0"/><ofd:AbbreviatedData>M 0 14.5125 L 0 0 L 0.75 0.7499 L 0.75 13.7625 C </ofd:AbbreviatedData></ofd:PathObject><ofd:PathObject ID="37" CTM="0.3528 0 0 0.3528 0 0" Boundary="188.7141 20.664 0.2646 62.5607" Stroke="false" Fill="true"><ofd:FillColor Value="0 0 0"/><ofd:AbbreviatedData>M 0 177.3375 L 0 0 L 0.7499 0 L 0.7499 177.3375 C </ofd:AbbreviatedData></ofd:PathObject><ofd:PathObject ID="38" CTM="0.3528 0 0 0.3528 0 0" Boundary="15.2268 25.3868 16.6026 0.2646" Stroke="false" Fill="true"><ofd:FillColor Value="0 0 0"/><ofd:AbbreviatedData>M 0 0 L 47.0625 0 L 46.3125 0.7501 L 0.75 0.7501 C </ofd:AbbreviatedData></ofd:PathObject><ofd:PathObject ID="39" CTM="0.3528 0 0 0.3528 0 0" Boundary="31.5648 25.3868 0.2646 5.1197" Stroke="false" Fill="true"><ofd:FillColor Value="0 0 0"/><ofd:AbbreviatedData>M 0.75 0 L 0.75 14.5125 L 0 13.7626 L 0 0.7501 C </ofd:AbbreviatedData></ofd:PathObject><ofd:PathObject ID="40" CTM="0.3528 0 0 0.3528 0 0" Boundary="15.2268 30.2419 16.6026 0.2646" Stroke="false" Fill="true"><ofd:FillColor Value="0 0 0"/><ofd:AbbreviatedData>M 47.0625 0.7499 L 0 0.7499 L 0.75 0 L 46.3125 0 C </ofd:AbbreviatedData></ofd:PathObject><ofd:PathObject ID="41" CTM="0.3528 0 0 0.3528 0 0" Boundary="15.2268 25.3868 0.2646 5.1197" Stroke="false" Fill="true"><ofd:FillColor Value="0 0 0"/><ofd:AbbreviatedData>M 0 14.5125 L 0 0 L 0.75 0.7501 L 0.75 13.7626 C </ofd:AbbreviatedData></ofd:PathObject><ofd:PathObject ID="42" CTM="0.3528 0 0 0.3528 0 0" Boundary="31.5648 25.3868 67.1909 0.2646" Stroke="false" Fill="true"><ofd:FillColor Value="0 0 0"/><ofd:AbbreviatedData>M 0 0 L 190.4625 0 L 189.7125 0.7501 L 0.75 0.7501 C </ofd:AbbreviatedData></ofd:PathObject><ofd:PathObject ID="43" CTM="0.3528 0 0 0.3528 0 0" Boundary="98.4911 25.3868 0.2646 5.1197" Stroke="false" Fill="true"><ofd:FillColor Value="0 0 0"/><ofd:AbbreviatedData>M 0.75 0 L 0.75 14.5125 L 0 13.7626 L 0 0.7501 C </ofd:AbbreviatedData></ofd:PathObject><ofd:PathObject ID="44" CTM="0.3528 0 0 0.3528 0 0" Boundary="31.5648 30.2419 67.1909 0.2646" Stroke="false" Fill="true"><ofd:FillColor Value="0 0 0"/><ofd:AbbreviatedData>M 190.4625 0.7499 L 0 0.7499 L 0.75 0 L 189.7125 0 C </ofd:AbbreviatedData></ofd:PathObject><ofd:PathObject ID="45" CTM="0.3528 0 0 0.3528 0 0" Boundary="31.5648 25.3868 0.2646 5.1197" Stroke="false" Fill="true"><ofd:FillColor Value="0 0 0"/><ofd:AbbreviatedData>M 0 14.5125 L 0 0 L 0.75 0.7501 L 0.75 13.7626 C </ofd:AbbreviatedData></ofd:PathObject><ofd:PathObject ID="46" CTM="0.3528 0 0 0.3528 0 0" Boundary="105.4497 25.3868 16.6026 0.2646" Stroke="false" Fill="true"><ofd:FillColor Value="0 0 0"/><ofd:AbbreviatedData>M 0 0 L 47.0625 0 L 46.3125 0.7501 L 0.75 0.7501 C </ofd:AbbreviatedData></ofd:PathObject><ofd:PathObject ID="47" CTM="0.3528 0 0 0.3528 0 0" Boundary="121.7877 25.3868 0.2646 5.1197" Stroke="false" Fill="true"><ofd:FillColor Value="0 0 0"/><ofd:AbbreviatedData>M 0.75 0 L 0.75 14.5125 L 0 13.7626 L 0 0.7501 C </ofd:AbbreviatedData></ofd:PathObject><ofd:PathObject ID="48" CTM="0.3528 0 0 0.3528 0 0" Boundary="105.4497 30.2419 16.6026 0.2646" Stroke="false" Fill="true"><ofd:FillColor Value="0 0 0"/><ofd:AbbreviatedData>M 47.0625 0.7499 L 0 0.7499 L 0.75 0 L 46.3125 0 C </ofd:AbbreviatedData></ofd:PathObject><ofd:PathObject ID="49" CTM="0.3528 0 0 0.3528 0 0" Boundary="105.4497 25.3868 0.2646 5.1197" Stroke="false" Fill="true"><ofd:FillColor Value="0 0 0"/><ofd:AbbreviatedData>M 0 14.5125 L 0 0 L 0.75 0.7501 L 0.75 13.7626 C </ofd:AbbreviatedData></ofd:PathObject><ofd:PathObject ID="50" CTM="0.3528 0 0 0.3528 0 0" Boundary="121.7877 25.3868 67.1909 0.2646" Stroke="false" Fill="true"><ofd:FillColor Value="0 0 0"/><ofd:AbbreviatedData>M 0 0 L 190.4625 0 L 189.7126 0.7501 L 0.75 0.7501 C </ofd:AbbreviatedData></ofd:PathObject><ofd:PathObject ID="51" CTM="0.3528 0 0 0.3528 0 0" Boundary="188.7141 25.3868 0.2646 5.1197" Stroke="false" Fill="true"><ofd:FillColor Value="0 0 0"/><ofd:AbbreviatedData>M 0.7499 0 L 0.7499 14.5125 L 0 13.7626 L 0 0.7501 C </ofd:AbbreviatedData></ofd:PathObject><ofd:PathObject ID="52" CTM="0.3528 0 0 0.3528 0 0" Boundary="121.7877 30.2419 67.1909 0.2646" Stroke="false" Fill="true"><ofd:FillColor Value="0 0 0"/><ofd:AbbreviatedData>M 190.4625 0.7499 L 0 0.7499 L 0.75 0 L 189.7126 0 C </ofd:AbbreviatedData></ofd:PathObject><ofd:PathObject ID="53" CTM="0.3528 0 0 0.3528 0 0" Boundary="121.7877 25.3868 0.2646 5.1197" Stroke="false" Fill="true"><ofd:FillColor Value="0 0 0"/><ofd:AbbreviatedData>M 0 14.5125 L 0 0 L 0.75 0.7501 L 0.75 13.7626 C </ofd:AbbreviatedData></ofd:PathObject><ofd:PathObject ID="54" CTM="0.3528 0 0 0.3528 0 0" Boundary="15.2268 30.2419 16.6026 0.2646" Stroke="false" Fill="true"><ofd:FillColor Value="0 0 0"/><ofd:AbbreviatedData>M 0 0 L 47.0625 0 L 46.3125 0.7499 L 0.75 0.7499 C </ofd:AbbreviatedData></ofd:PathObject><ofd:PathObject ID="55" CTM="0.3528 0 0 0.3528 0 0" Boundary="31.5648 30.2419 0.2646 5.1197" Stroke="false" Fill="true"><ofd:FillColor Value="0 0 0"/><ofd:AbbreviatedData>M 0.75 0 L 0.75 14.5125 L 0 13.7625 L 0 0.7499 C </ofd:AbbreviatedData></ofd:PathObject><ofd:PathObject ID="56" CTM="0.3528 0 0 0.3528 0 0" Boundary="15.2268 35.097 16.6026 0.2646" Stroke="false" Fill="true"><ofd:FillColor Value="0 0 0"/><ofd:AbbreviatedData>M 47.0625 0.75 L 0 0.75 L 0.75 0 L 46.3125 0 C </ofd:AbbreviatedData></ofd:PathObject><ofd:PathObject ID="57" CTM="0.3528 0 0 0.3528 0 0" Boundary="15.2268 30.2419 0.2646 5.1197" Stroke="false" Fill="true"><ofd:FillColor Value="0 0 0"/><ofd:AbbreviatedData>M 0 14.5125 L 0 0 L 0.75 0.7499 L 0.75 13.7625 C </ofd:AbbreviatedData></ofd:PathObject><ofd:PathObject ID="58" CTM="0.3528 0 0 0.3528 0 0" Boundary="31.5648 30.2419 67.1909 0.2646" Stroke="false" Fill="true"><ofd:FillColor Value="0 0 0"/><ofd:AbbreviatedData>M 0 0 L 190.4625 0 L 189.7125 0.7499 L 0.75 0.7499 C </ofd:AbbreviatedData></ofd:PathObject><ofd:PathObject ID="59" CTM="0.3528 0 0 0.3528 0 0" Boundary="98.4911 30.2419 0.2646 5.1197" Stroke="false" Fill="true"><ofd:FillColor Value="0 0 0"/><ofd:AbbreviatedData>M 0.75 0 L 0.75 14.5125 L 0 13.7625 L 0 0.7499 C </ofd:AbbreviatedData></ofd:PathObject><ofd:PathObject ID="60" CTM="0.3528 0 0 0.3528 0 0" Boundary="31.5648 35.097 67.1909 0.2646" Stroke="false" Fill="true"><ofd:FillColor Value="0 0 0"/><ofd:AbbreviatedData>M 190.4625 0.75 L 0 0.75 L 0.75 0 L 189.7125 0 C </ofd:AbbreviatedData></ofd:PathObject><ofd:PathObject ID="61" CTM="0.3528 0 0 0.3528 0 0" Boundary="31.5648 30.2419 0.2646 5.1197" Stroke="false" Fill="true"><ofd:FillColor Value="0 0 0"/><ofd:AbbreviatedData>M 0 14.5125 L 0 0 L 0.75 0.7499 L 0.75 13.7625 C </ofd:AbbreviatedData></ofd:PathObject><ofd:PathObject ID="62" CTM="0.3528 0 0 0.3528 0 0" Boundary="105.4497 30.2419 16.6026 0.2646" Stroke="false" Fill="true"><ofd:FillColor Value="0 0 0"/><ofd:AbbreviatedData>M 0 0 L 47.0625 0 L 46.3125 0.7499 L 0.75 0.7499 C </ofd:AbbreviatedData></ofd:PathObject><ofd:PathObject ID="63" CTM="0.3528 0 0 0.3528 0 0" Boundary="121.7877 30.2419 0.2646 5.1197" Stroke="false" Fill="true"><ofd:FillColor Value="0 0 0"/><ofd:AbbreviatedData>M 0.75 0 L 0.75 14.5125 L 0 13.7625 L 0 0.7499 C </ofd:AbbreviatedData></ofd:PathObject><ofd:PathObject ID="64" CTM="0.3528 0 0 0.3528 0 0" Boundary="105.4497 35.097 16.6026 0.2646" Stroke="false" Fill="true"><ofd:FillColor Value="0 0 0"/><ofd:AbbreviatedData>M 47.0625 0.75 L 0 0.75 L 0.75 0 L 46.3125 0 C </ofd:AbbreviatedData></ofd:PathObject><ofd:PathObject ID="65" CTM="0.3528 0 0 0.3528 0 0" Boundary="105.4497 30.2419 0.2646 5.1197" Stroke="false" Fill="true"><ofd:FillColor Value="0 0 0"/><ofd:AbbreviatedData>M 0 14.5125 L 0 0 L 0.75 0.7499 L 0.75 13.7625 C </ofd:AbbreviatedData></ofd:PathObject><ofd:PathObject ID="66" CTM="0.3528 0 0 0.3528 0 0" Boundary="121.7877 30.2419 67.1909 0.2646" Stroke="false" Fill="true"><ofd:FillColor Value="0 0 0"/><ofd:AbbreviatedData>M 0 0 L 190.4625 0 L 189.7126 0.7499 L 0.75 0.7499 C </ofd:AbbreviatedData></ofd:PathObject><ofd:PathObject ID="67" CTM="0.3528 0 0 0.3528 0 0" Boundary="188.7141 30.2419 0.2646 5.1197" Stroke="false" Fill="true"><ofd:FillColor Value="0 0 0"/><ofd:AbbreviatedData>M 0.7499 0 L 0.7499 14.5125 L 0 13.7625 L 0 0.7499 C </ofd:AbbreviatedData></ofd:PathObject><ofd:PathObject ID="68" CTM="0.3528 0 0 0.3528 0 0" Boundary="121.7877 35.097 67.1909 0.2646" Stroke="false" Fill="true"><ofd:FillColor Value="0 0 0"/><ofd:AbbreviatedData>M 190.4625 0.75 L 0 0.75 L 0.75 0 L 189.7126 0 C </ofd:AbbreviatedData></ofd:PathObject><ofd:PathObject ID="69" CTM="0.3528 0 0 0.3528 0 0" Boundary="121.7877 30.2419 0.2646 5.1197" Stroke="false" Fill="true"><ofd:FillColor Value="0 0 0"/><ofd:AbbreviatedData>M 0 14.5125 L 0 0 L 0.75 0.7499 L 0.75 13.7625 C </ofd:AbbreviatedData></ofd:PathObject><ofd:PathObject ID="70" CTM="0.3528 0 0 0.3528 0 0" Boundary="8.2682 35.097 23.5611 0.2646" Stroke="false" Fill="true"><ofd:FillColor Value="0 0 0"/><ofd:Clips TransFlag="false"><ofd:Clip><ofd:Area CTM="0.3528 0 0 0.3528 0 0"><ofd:Path Boundary="0.375 -99.4875 547.65 841.8375" Stroke="false" Fill="true"><ofd:AbbreviatedData>M 0 0 L 547.65 0 L 547.65 841.8375 L 0 841.8375 C </ofd:AbbreviatedData></ofd:Path></ofd:Area></ofd:Clip></ofd:Clips><ofd:AbbreviatedData>M 0 0 L 66.7875 0 L 66.0375 0.75 L 0.75 0.75 C </ofd:AbbreviatedData></ofd:PathObject><ofd:PathObject ID="72" CTM="0.3528 0 0 0.3528 0 0" Boundary="31.5648 35.097 0.2646 5.5563" Stroke="false" Fill="true"><ofd:FillColor Value="0 0 0"/><ofd:AbbreviatedData>M 0.75 0 L 0.75 15.75 L 0 15 L 0 0.75 C </ofd:AbbreviatedData></ofd:PathObject><ofd:PathObject ID="73" CTM="0.3528 0 0 0.3528 0 0" Boundary="8.2682 40.3886 23.5611 0.2646" Stroke="false" Fill="true"><ofd:FillColor Value="0 0 0"/><ofd:Clips TransFlag="false"><ofd:Clip><ofd:Area CTM="0.3528 0 0 0.3528 0 0"><ofd:Path Boundary="0.375 -114.4875 547.65 841.8375" Stroke="false" Fill="true"><ofd:AbbreviatedData>M 0 0 L 547.65 0 L 547.65 841.8375 L 0 841.8375 C </ofd:AbbreviatedData></ofd:Path></ofd:Area></ofd:Clip></ofd:Clips><ofd:AbbreviatedData>M 66.7875 0.75 L 0 0.75 L 0.75 0 L 66.0375 0 C </ofd:AbbreviatedData></ofd:PathObject><ofd:PathObject ID="75" CTM="0.3528 0 0 0.3528 0 0" Boundary="8.2682 35.097 0.2646 5.5563" Stroke="false" Fill="true"><ofd:FillColor Value="0 0 0"/><ofd:Clips TransFlag="false"><ofd:Clip><ofd:Area CTM="0.3528 0 0 0.3528 0 0"><ofd:Path Boundary="0.375 -99.4875 547.65 841.8375" Stroke="false" Fill="true"><ofd:AbbreviatedData>M 0 0 L 547.65 0 L 547.65 841.8375 L 0 841.8375 C </ofd:AbbreviatedData></ofd:Path></ofd:Area></ofd:Clip></ofd:Clips><ofd:AbbreviatedData>M 0 15.75 L 0 0 L 0.75 0.75 L 0.75 15 C </ofd:AbbreviatedData></ofd:PathObject><ofd:PathObject ID="77" CTM="0.3528 0 0 0.3528 0 0" Boundary="31.5648 35.097 90.3552 0.2646" Stroke="false" Fill="true"><ofd:FillColor Value="0 0 0"/><ofd:AbbreviatedData>M 0 0 L 256.125 0 L 256.125 0.75 L 0.75 0.75 C </ofd:AbbreviatedData></ofd:PathObject><ofd:PathObject ID="78" CTM="0.3528 0 0 0.3528 0 0" Boundary="31.5648 40.3886 90.3552 0.2646" Stroke="false" Fill="true"><ofd:FillColor Value="0 0 0"/><ofd:AbbreviatedData>M 256.125 0.75 L 0 0.75 L 0.75 0 L 256.125 0 C </ofd:AbbreviatedData></ofd:PathObject><ofd:PathObject ID="79" CTM="0.3528 0 0 0.3528 0 0" Boundary="31.5648 35.097 0.2646 5.5563" Stroke="false" Fill="true"><ofd:FillColor Value="0 0 0"/><ofd:AbbreviatedData>M 0 15.75 L 0 0 L 0.75 0.75 L 0.75 15 C </ofd:AbbreviatedData></ofd:PathObject><ofd:PathObject ID="80" CTM="0.3528 0 0 0.3528 0 0" Boundary="121.92 35.097 66.9264 0.2646" Stroke="false" Fill="true"><ofd:FillColor Value="0 0 0"/><ofd:AbbreviatedData>M 0 0 L 189.7125 0 L 189.7125 0.75 L 0 0.75 C </ofd:AbbreviatedData></ofd:PathObject><ofd:PathObject ID="81" CTM="0.3528 0 0 0.3528 0 0" Boundary="121.92 40.3886 66.9264 0.2646" Stroke="false" Fill="true"><ofd:FillColor Value="0 0 0"/><ofd:AbbreviatedData>M 189.7125 0.75 L 0 0.75 L 0 0 L 189.7125 0 C </ofd:AbbreviatedData></ofd:PathObject><ofd:PathObject ID="82" CTM="0.3528 0 0 0.3528 0 0" Boundary="8.2682 40.3886 23.5611 0.2646" Stroke="false" Fill="true"><ofd:FillColor Value="0 0 0"/><ofd:Clips TransFlag="false"><ofd:Clip><ofd:Area CTM="0.3528 0 0 0.3528 0 0"><ofd:Path Boundary="0.375 -114.4875 547.65 841.8375" Stroke="false" Fill="true"><ofd:AbbreviatedData>M 0 0 L 547.65 0 L 547.65 841.8375 L 0 841.8375 C </ofd:AbbreviatedData></ofd:Path></ofd:Area></ofd:Clip></ofd:Clips><ofd:AbbreviatedData>M 0 0 L 66.7875 0 L 66.0375 0.75 L 0.75 0.75 C </ofd:AbbreviatedData></ofd:PathObject><ofd:PathObject ID="84" CTM="0.3528 0 0 0.3528 0 0" Boundary="31.5648 40.3886 0.2646 5.1197" Stroke="false" Fill="true"><ofd:FillColor Value="0 0 0"/><ofd:AbbreviatedData>M 0.75 0 L 0.75 14.5125 L 0 13.7625 L 0 0.75 C </ofd:AbbreviatedData></ofd:PathObject><ofd:PathObject ID="85" CTM="0.3528 0 0 0.3528 0 0" Boundary="8.2682 45.2438 23.5611 0.2646" Stroke="false" Fill="true"><ofd:FillColor Value="0 0 0"/><ofd:Clips TransFlag="false"><ofd:Clip><ofd:Area CTM="0.3528 0 0 0.3528 0 0"><ofd:Path Boundary="0.375 -128.25 547.65 841.8375" Stroke="false" Fill="true"><ofd:AbbreviatedData>M 0 0 L 547.65 0 L 547.65 841.8375 L 0 841.8375 C </ofd:AbbreviatedData></ofd:Path></ofd:Area></ofd:Clip></ofd:Clips><ofd:AbbreviatedData>M 66.7875 0.75 L 0 0.75 L 0.75 0 L 66.0375 0 C </ofd:AbbreviatedData></ofd:PathObject><ofd:PathObject ID="87" CTM="0.3528 0 0 0.3528 0 0" Boundary="8.2682 40.3886 0.2646 5.1197" Stroke="false" Fill="true"><ofd:FillColor Value="0 0 0"/><ofd:Clips TransFlag="false"><ofd:Clip><ofd:Area CTM="0.3528 0 0 0.3528 0 0"><ofd:Path Boundary="0.375 -114.4875 547.65 841.8375" Stroke="false" Fill="true"><ofd:AbbreviatedData>M 0 0 L 547.65 0 L 547.65 841.8375 L 0 841.8375 C </ofd:AbbreviatedData></ofd:Path></ofd:Area></ofd:Clip></ofd:Clips><ofd:AbbreviatedData>M 0 14.5125 L 0 0 L 0.75 0.75 L 0.75 13.7625 C </ofd:AbbreviatedData></ofd:PathObject><ofd:PathObject ID="89" CTM="0.3528 0 0 0.3528 0 0" Boundary="31.5648 40.3886 67.1909 0.2646" Stroke="false" Fill="true"><ofd:FillColor Value="0 0 0"/><ofd:AbbreviatedData>M 0 0 L 190.4625 0 L 189.7125 0.75 L 0.75 0.75 C </ofd:AbbreviatedData></ofd:PathObject><ofd:PathObject ID="90" CTM="0.3528 0 0 0.3528 0 0" Boundary="98.4911 40.3886 0.2646 5.1197" Stroke="false" Fill="true"><ofd:FillColor Value="0 0 0"/><ofd:AbbreviatedData>M 0.75 0 L 0.75 14.5125 L 0 13.7625 L 0 0.75 C </ofd:AbbreviatedData></ofd:PathObject><ofd:PathObject ID="91" CTM="0.3528 0 0 0.3528 0 0" Boundary="31.5648 45.2438 67.1909 0.2646" Stroke="false" Fill="true"><ofd:FillColor Value="0 0 0"/><ofd:AbbreviatedData>M 190.4625 0.75 L 0 0.75 L 0.75 0 L 189.7125 0 C </ofd:AbbreviatedData></ofd:PathObject><ofd:PathObject ID="92" CTM="0.3528 0 0 0.3528 0 0" Boundary="31.5648 40.3886 0.2646 5.1197" Stroke="false" Fill="true"><ofd:FillColor Value="0 0 0"/><ofd:AbbreviatedData>M 0 14.5125 L 0 0 L 0.75 0.75 L 0.75 13.7625 C </ofd:AbbreviatedData></ofd:PathObject><ofd:PathObject ID="93" CTM="0.3528 0 0 0.3528 0 0" Boundary="98.4911 40.3886 23.5612 0.2646" Stroke="false" Fill="true"><ofd:FillColor Value="0 0 0"/><ofd:AbbreviatedData>M 0 0 L 66.7875 0 L 66.0375 0.75 L 0.75 0.75 C </ofd:AbbreviatedData></ofd:PathObject><ofd:PathObject ID="94" CTM="0.3528 0 0 0.3528 0 0" Boundary="121.7877 40.3886 0.2646 5.1197" Stroke="false" Fill="true"><ofd:FillColor Value="0 0 0"/><ofd:AbbreviatedData>M 0.75 0 L 0.75 14.5125 L 0 13.7625 L 0 0.75 C </ofd:AbbreviatedData></ofd:PathObject><ofd:PathObject ID="95" CTM="0.3528 0 0 0.3528 0 0" Boundary="98.4911 45.2438 23.5612 0.2646" Stroke="false" Fill="true"><ofd:FillColor Value="0 0 0"/><ofd:AbbreviatedData>M 66.7875 0.75 L 0 0.75 L 0.75 0 L 66.0375 0 C </ofd:AbbreviatedData></ofd:PathObject><ofd:PathObject ID="96" CTM="0.3528 0 0 0.3528 0 0" Boundary="98.4911 40.3886 0.2646 5.1197" Stroke="false" Fill="true"><ofd:FillColor Value="0 0 0"/><ofd:AbbreviatedData>M 0 14.5125 L 0 0 L 0.75 0.75 L 0.75 13.7625 C </ofd:AbbreviatedData></ofd:PathObject><ofd:PathObject ID="97" CTM="0.3528 0 0 0.3528 0 0" Boundary="121.7877 40.3886 67.1909 0.2646" Stroke="false" Fill="true"><ofd:FillColor Value="0 0 0"/><ofd:AbbreviatedData>M 0 0 L 190.4625 0 L 189.7126 0.75 L 0.75 0.75 C </ofd:AbbreviatedData></ofd:PathObject><ofd:PathObject ID="98" CTM="0.3528 0 0 0.3528 0 0" Boundary="188.7141 40.3886 0.2646 5.1197" Stroke="false" Fill="true"><ofd:FillColor Value="0 0 0"/><ofd:AbbreviatedData>M 0.7499 0 L 0.7499 14.5125 L 0 13.7625 L 0 0.75 C </ofd:AbbreviatedData></ofd:PathObject><ofd:PathObject ID="99" CTM="0.3528 0 0 0.3528 0 0" Boundary="121.7877 45.2438 67.1909 0.2646" Stroke="false" Fill="true"><ofd:FillColor Value="0 0 0"/><ofd:AbbreviatedData>M 190.4625 0.75 L 0 0.75 L 0.75 0 L 189.7126 0 C </ofd:AbbreviatedData></ofd:PathObject><ofd:PathObject ID="100" CTM="0.3528 0 0 0.3528 0 0" Boundary="121.7877 40.3886 0.2646 5.1197" Stroke="false" Fill="true"><ofd:FillColor Value="0 0 0"/><ofd:AbbreviatedData>M 0 14.5125 L 0 0 L 0.75 0.75 L 0.75 13.7625 C </ofd:AbbreviatedData></ofd:PathObject><ofd:PathObject ID="101" CTM="0.3528 0 0 0.3528 0 0" Boundary="8.2682 45.2438 23.5611 0.2646" Stroke="false" Fill="true"><ofd:FillColor Value="0 0 0"/><ofd:Clips TransFlag="false"><ofd:Clip><ofd:Area CTM="0.3528 0 0 0.3528 0 0"><ofd:Path Boundary="0.375 -128.25 547.65 841.8375" Stroke="false" Fill="true"><ofd:AbbreviatedData>M 0 0 L 547.65 0 L 547.65 841.8375 L 0 841.8375 C </ofd:AbbreviatedData></ofd:Path></ofd:Area></ofd:Clip></ofd:Clips><ofd:AbbreviatedData>M 0 0 L 66.7875 0 L 66.0375 0.75 L 0.75 0.75 C </ofd:AbbreviatedData></ofd:PathObject><ofd:PathObject ID="103" CTM="0.3528 0 0 0.3528 0 0" Boundary="31.5648 45.2438 0.2646 5.1197" Stroke="false" Fill="true"><ofd:FillColor Value="0 0 0"/><ofd:AbbreviatedData>M 0.75 0 L 0.75 14.5125 L 0 13.7625 L 0 0.75 C </ofd:AbbreviatedData></ofd:PathObject><ofd:PathObject ID="104" CTM="0.3528 0 0 0.3528 0 0" Boundary="8.2682 50.0989 23.5611 0.2646" Stroke="false" Fill="true"><ofd:FillColor Value="0 0 0"/><ofd:Clips TransFlag="false"><ofd:Clip><ofd:Area CTM="0.3528 0 0 0.3528 0 0"><ofd:Path Boundary="0.375 -142.0125 547.65 841.8375" Stroke="false" Fill="true"><ofd:AbbreviatedData>M 0 0 L 547.65 0 L 547.65 841.8375 L 0 841.8375 C </ofd:AbbreviatedData></ofd:Path></ofd:Area></ofd:Clip></ofd:Clips><ofd:AbbreviatedData>M 66.7875 0.75 L 0 0.75 L 0.75 0 L 66.0375 0 C </ofd:AbbreviatedData></ofd:PathObject><ofd:PathObject ID="106" CTM="0.3528 0 0 0.3528 0 0" Boundary="8.2682 45.2438 0.2646 5.1197" Stroke="false" Fill="true"><ofd:FillColor Value="0 0 0"/><ofd:Clips TransFlag="false"><ofd:Clip><ofd:Area CTM="0.3528 0 0 0.3528 0 0"><ofd:Path Boundary="0.375 -128.25 547.65 841.8375" Stroke="false" Fill="true"><ofd:AbbreviatedData>M 0 0 L 547.65 0 L 547.65 841.8375 L 0 841.8375 C </ofd:AbbreviatedData></ofd:Path></ofd:Area></ofd:Clip></ofd:Clips><ofd:AbbreviatedData>M 0 14.5125 L 0 0 L 0.75 0.75 L 0.75 13.7625 C </ofd:AbbreviatedData></ofd:PathObject><ofd:PathObject ID="108" CTM="0.3528 0 0 0.3528 0 0" Boundary="31.5648 45.2438 67.1909 0.2646" Stroke="false" Fill="true"><ofd:FillColor Value="0 0 0"/><ofd:AbbreviatedData>M 0 0 L 190.4625 0 L 189.7125 0.75 L 0.75 0.75 C </ofd:AbbreviatedData></ofd:PathObject><ofd:PathObject ID="109" CTM="0.3528 0 0 0.3528 0 0" Boundary="98.4911 45.2438 0.2646 5.1197" Stroke="false" Fill="true"><ofd:FillColor Value="0 0 0"/><ofd:AbbreviatedData>M 0.75 0 L 0.75 14.5125 L 0 13.7625 L 0 0.75 C </ofd:AbbreviatedData></ofd:PathObject><ofd:PathObject ID="110" CTM="0.3528 0 0 0.3528 0 0" Boundary="31.5648 50.0989 67.1909 0.2646" Stroke="false" Fill="true"><ofd:FillColor Value="0 0 0"/><ofd:AbbreviatedData>M 190.4625 0.75 L 0 0.75 L 0.75 0 L 189.7125 0 C </ofd:AbbreviatedData></ofd:PathObject><ofd:PathObject ID="111" CTM="0.3528 0 0 0.3528 0 0" Boundary="31.5648 45.2438 0.2646 5.1197" Stroke="false" Fill="true"><ofd:FillColor Value="0 0 0"/><ofd:AbbreviatedData>M 0 14.5125 L 0 0 L 0.75 0.75 L 0.75 13.7625 C </ofd:AbbreviatedData></ofd:PathObject><ofd:PathObject ID="112" CTM="0.3528 0 0 0.3528 0 0" Boundary="98.4911 45.2438 23.5612 0.2646" Stroke="false" Fill="true"><ofd:FillColor Value="0 0 0"/><ofd:AbbreviatedData>M 0 0 L 66.7875 0 L 66.0375 0.75 L 0.75 0.75 C </ofd:AbbreviatedData></ofd:PathObject><ofd:PathObject ID="113" CTM="0.3528 0 0 0.3528 0 0" Boundary="121.7877 45.2438 0.2646 5.1197" Stroke="false" Fill="true"><ofd:FillColor Value="0 0 0"/><ofd:AbbreviatedData>M 0.75 0 L 0.75 14.5125 L 0 13.7625 L 0 0.75 C </ofd:AbbreviatedData></ofd:PathObject><ofd:PathObject ID="114" CTM="0.3528 0 0 0.3528 0 0" Boundary="98.4911 50.0989 23.5612 0.2646" Stroke="false" Fill="true"><ofd:FillColor Value="0 0 0"/><ofd:AbbreviatedData>M 66.7875 0.75 L 0 0.75 L 0.75 0 L 66.0375 0 C </ofd:AbbreviatedData></ofd:PathObject><ofd:PathObject ID="115" CTM="0.3528 0 0 0.3528 0 0" Boundary="98.4911 45.2438 0.2646 5.1197" Stroke="false" Fill="true"><ofd:FillColor Value="0 0 0"/><ofd:AbbreviatedData>M 0 14.5125 L 0 0 L 0.75 0.75 L 0.75 13.7625 C </ofd:AbbreviatedData></ofd:PathObject><ofd:PathObject ID="116" CTM="0.3528 0 0 0.3528 0 0" Boundary="121.7877 45.2438 67.1909 0.2646" Stroke="false" Fill="true"><ofd:FillColor Value="0 0 0"/><ofd:AbbreviatedData>M 0 0 L 190.4625 0 L 189.7126 0.75 L 0.75 0.75 C </ofd:AbbreviatedData></ofd:PathObject><ofd:PathObject ID="117" CTM="0.3528 0 0 0.3528 0 0" Boundary="188.7141 45.2438 0.2646 5.1197" Stroke="false" Fill="true"><ofd:FillColor Value="0 0 0"/><ofd:AbbreviatedData>M 0.7499 0 L 0.7499 14.5125 L 0 13.7625 L 0 0.75 C </ofd:AbbreviatedData></ofd:PathObject><ofd:PathObject ID="118" CTM="0.3528 0 0 0.3528 0 0" Boundary="121.7877 50.0989 67.1909 0.2646" Stroke="false" Fill="true"><ofd:FillColor Value="0 0 0"/><ofd:AbbreviatedData>M 190.4625 0.75 L 0 0.75 L 0.75 0 L 189.7126 0 C </ofd:AbbreviatedData></ofd:PathObject><ofd:PathObject ID="119" CTM="0.3528 0 0 0.3528 0 0" Boundary="121.7877 45.2438 0.2646 5.1197" Stroke="false" Fill="true"><ofd:FillColor Value="0 0 0"/><ofd:AbbreviatedData>M 0 14.5125 L 0 0 L 0.75 0.75 L 0.75 13.7625 C </ofd:AbbreviatedData></ofd:PathObject><ofd:PathObject ID="120" CTM="0.3528 0 0 0.3528 0 0" Boundary="8.2682 50.0989 90.4875 0.2646" Stroke="false" Fill="true"><ofd:FillColor Value="0 0 0"/><ofd:Clips TransFlag="false"><ofd:Clip><ofd:Area CTM="0.3528 0 0 0.3528 0 0"><ofd:Path Boundary="0.375 -142.0125 547.65 841.8375" Stroke="false" Fill="true"><ofd:AbbreviatedData>M 0 0 L 547.65 0 L 547.65 841.8375 L 0 841.8375 C </ofd:AbbreviatedData></ofd:Path></ofd:Area></ofd:Clip></ofd:Clips><ofd:AbbreviatedData>M 0 0 L 256.5 0 L 255.75 0.75 L 0.75 0.75 C </ofd:AbbreviatedData></ofd:PathObject><ofd:PathObject ID="122" CTM="0.3528 0 0 0.3528 0 0" Boundary="98.4911 50.0989 0.2646 33.2581" Stroke="false" Fill="true"><ofd:FillColor Value="0 0 0"/><ofd:AbbreviatedData>M 0.75 0 L 0.75 94.275 L 0 93.525 L 0 0.75 C </ofd:AbbreviatedData></ofd:PathObject><ofd:PathObject ID="123" CTM="0.3528 0 0 0.3528 0 0" Boundary="8.2682 83.0924 90.4875 0.2646" Stroke="false" Fill="true"><ofd:FillColor Value="0 0 0"/><ofd:Clips TransFlag="false"><ofd:Clip><ofd:Area CTM="0.3528 0 0 0.3528 0 0"><ofd:Path Boundary="0.375 -235.5375 547.65 841.8375" Stroke="false" Fill="true"><ofd:AbbreviatedData>M 0 0 L 547.65 0 L 547.65 841.8375 L 0 841.8375 C </ofd:AbbreviatedData></ofd:Path></ofd:Area></ofd:Clip></ofd:Clips><ofd:AbbreviatedData>M 256.5 0.75 L 0 0.75 L 0.75 0 L 255.75 0 C </ofd:AbbreviatedData></ofd:PathObject><ofd:PathObject ID="125" CTM="0.3528 0 0 0.3528 0 0" Boundary="8.2682 50.0989 0.2646 33.2581" Stroke="false" Fill="true"><ofd:FillColor Value="0 0 0"/><ofd:Clips TransFlag="false"><ofd:Clip><ofd:Area CTM="0.3528 0 0 0.3528 0 0"><ofd:Path Boundary="0.375 -142.0125 547.65 841.8375" Stroke="false" Fill="true"><ofd:AbbreviatedData>M 0 0 L 547.65 0 L 547.65 841.8375 L 0 841.8375 C </ofd:AbbreviatedData></ofd:Path></ofd:Area></ofd:Clip></ofd:Clips><ofd:AbbreviatedData>M 0 94.275 L 0 0 L 0.75 0.75 L 0.75 93.525 C </ofd:AbbreviatedData></ofd:PathObject><ofd:PathObject ID="127" CTM="0.3528 0 0 0.3528 0 0" Boundary="98.4911 50.0989 90.4875 0.2646" Stroke="false" Fill="true"><ofd:FillColor Value="0 0 0"/><ofd:AbbreviatedData>M 0 0 L 256.5 0 L 255.7501 0.75 L 0.75 0.75 C </ofd:AbbreviatedData></ofd:PathObject><ofd:PathObject ID="128" CTM="0.3528 0 0 0.3528 0 0" Boundary="188.7141 50.0989 0.2646 33.2581" Stroke="false" Fill="true"><ofd:FillColor Value="0 0 0"/><ofd:AbbreviatedData>M 0.7499 0 L 0.7499 94.275 L 0 93.525 L 0 0.75 C </ofd:AbbreviatedData></ofd:PathObject><ofd:PathObject ID="129" CTM="0.3528 0 0 0.3528 0 0" Boundary="98.4911 83.0924 90.4875 0.2646" Stroke="false" Fill="true"><ofd:FillColor Value="0 0 0"/><ofd:AbbreviatedData>M 256.5 0.75 L 0 0.75 L 0.75 0 L 255.7501 0 C </ofd:AbbreviatedData></ofd:PathObject><ofd:PathObject ID="130" CTM="0.3528 0 0 0.3528 0 0" Boundary="98.4911 50.0989 0.2646 33.2581" Stroke="false" Fill="true"><ofd:FillColor Value="0 0 0"/><ofd:AbbreviatedData>M 0 94.275 L 0 0 L 0.75 0.75 L 0.75 93.525 C </ofd:AbbreviatedData></ofd:PathObject><ofd:TextObject ID="131" CTM="0.3528 0 0 0.3528 0 0" Boundary="10.1203 22.7892 3.3944 3.5286" Font="6" Size="10.0125"><ofd:CGTransform CodePosition="0" CodeCount="1" GlyphCount="1"><ofd:Glyphs>48</ofd:Glyphs></ofd:CGTransform><ofd:TextCode X="0" Y="8.6007">付</ofd:TextCode></ofd:TextObject><ofd:TextObject ID="132" CTM="0.3528 0 0 0.3528 0 0" Boundary="10.1203 26.3214 3.3803 3.5286" Font="6" Size="10.0125"><ofd:CGTransform CodePosition="0" CodeCount="1" GlyphCount="1"><ofd:Glyphs>117</ofd:Glyphs></ofd:CGTransform><ofd:TextCode X="0" Y="8.6007">款</ofd:TextCode></ofd:TextObject><ofd:TextObject ID="133" CTM="0.3528 0 0 0.3528 0 0" Boundary="10.1203 29.8536 3.3803 3.5286" Font="6" Size="10.0125"><ofd:CGTransform CodePosition="0" CodeCount="1" GlyphCount="1"><ofd:Glyphs>47</ofd:Glyphs></ofd:CGTransform><ofd:TextCode X="0" Y="8.6007">人</ofd:TextCode></ofd:TextObject><ofd:TextObject ID="134" CTM="0.3528 0 0 0.3528 0 0" Boundary="18.2298 21.4663 10.4164 3.5286" Font="6" Size="10.0125"><ofd:CGTransform CodePosition="0" CodeCount="3" GlyphCount="3"><ofd:Glyphs>57 36 133</ofd:Glyphs></ofd:CGTransform><ofd:TextCode X="0" Y="8.6007" DeltaX="10.0125 10.0125">全 称</ofd:TextCode></ofd:TextObject><ofd:TextObject ID="135" CTM="0.3528 0 0 0.3528 0 0" Boundary="32.3585 21.4663 20.9989 3.5286" Font="6" Size="10.0125"><ofd:CGTransform CodePosition="0" CodeCount="6" GlyphCount="6"><ofd:Glyphs>43 78 61 41 82 85</ofd:Glyphs></ofd:CGTransform><ofd:TextCode X="0" Y="8.6007" DeltaX="10.0125 10.0125 10.0125 10.0125 10.0125">中国农业大学</ofd:TextCode></ofd:TextObject><ofd:TextObject ID="136" CTM="0.3528 0 0 0.3528 0 0" Boundary="100.3432 22.7892 3.3944 3.5286" Font="6" Size="10.0125"><ofd:CGTransform CodePosition="0" CodeCount="1" GlyphCount="1"><ofd:Glyphs>102</ofd:Glyphs></ofd:CGTransform><ofd:TextCode X="0" Y="8.6007">收</ofd:TextCode></ofd:TextObject><ofd:TextObject ID="137" CTM="0.3528 0 0 0.3528 0 0" Boundary="100.3432 26.3214 3.3803 3.5286" Font="6" Size="10.0125"><ofd:CGTransform CodePosition="0" CodeCount="1" GlyphCount="1"><ofd:Glyphs>117</ofd:Glyphs></ofd:CGTransform><ofd:TextCode X="0" Y="8.6007">款</ofd:TextCode></ofd:TextObject><ofd:TextObject ID="138" CTM="0.3528 0 0 0.3528 0 0" Boundary="100.3432 29.8536 3.3803 3.5286" Font="6" Size="10.0125"><ofd:CGTransform CodePosition="0" CodeCount="1" GlyphCount="1"><ofd:Glyphs>47</ofd:Glyphs></ofd:CGTransform><ofd:TextCode X="0" Y="8.6007">人</ofd:TextCode></ofd:TextObject><ofd:TextObject ID="139" CTM="0.3528 0 0 0.3528 0 0" Boundary="108.4527 21.4663 10.4164 3.5286" Font="6" Size="10.0125"><ofd:CGTransform CodePosition="0" CodeCount="3" GlyphCount="3"><ofd:Glyphs>57 36 133</ofd:Glyphs></ofd:CGTransform><ofd:TextCode X="0" Y="8.6007" DeltaX="10.0125 10.0125">全 称</ofd:TextCode></ofd:TextObject><ofd:TextObject ID="140" CTM="0.3528 0 0 0.3528 0 0" Boundary="122.5815 21.4663 10.4588 3.5286" Font="6" Size="10.0125"><ofd:CGTransform CodePosition="0" CodeCount="3" GlyphCount="3"><ofd:Glyphs>112 54 83</ofd:Glyphs></ofd:CGTransform><ofd:TextCode X="0" Y="8.6007" DeltaX="10.0125 10.0125">李俊婕</ofd:TextCode></ofd:TextObject><ofd:TextObject ID="141" CTM="0.3528 0 0 0.3528 0 0" Boundary="190.6323 29.126 3.4086 3.5286" Font="6" Size="10.0125"><ofd:CGTransform CodePosition="0" CodeCount="1" GlyphCount="1"><ofd:Glyphs>169</ofd:Glyphs></ofd:CGTransform><ofd:TextCode X="0" Y="8.6007">︵</ofd:TextCode></ofd:TextObject><ofd:TextObject ID="142" CTM="0.3528 0 0 0.3528 0 0" Boundary="190.6323 32.6581 3.4086 3.5286" Font="6" Size="10.0125"><ofd:CGTransform CodePosition="0" CodeCount="1" GlyphCount="1"><ofd:Glyphs>55</ofd:Glyphs></ofd:CGTransform><ofd:TextCode X="0" Y="8.6007">借</ofd:TextCode></ofd:TextObject><ofd:TextObject ID="143" CTM="0.3528 0 0 0.3528 0 0" Boundary="190.6323 36.1903 3.3944 3.5286" Font="6" Size="10.0125"><ofd:CGTransform CodePosition="0" CodeCount="1" GlyphCount="1"><ofd:Glyphs>105</ofd:Glyphs></ofd:CGTransform><ofd:TextCode X="0" Y="8.6007">方</ofd:TextCode></ofd:TextObject><ofd:TextObject ID="144" CTM="0.3528 0 0 0.3528 0 0" Boundary="190.6323 39.7225 3.1472 3.5286" Font="6" Size="10.0125"><ofd:CGTransform CodePosition="0" CodeCount="1" GlyphCount="1"><ofd:Glyphs>77</ofd:Glyphs></ofd:CGTransform><ofd:TextCode X="0" Y="8.6007">回</ofd:TextCode></ofd:TextObject><ofd:TextObject ID="145" CTM="0.3528 0 0 0.3528 0 0" Boundary="190.6323 43.2547 3.3803 3.5286" Font="6" Size="10.0125"><ofd:CGTransform CodePosition="0" CodeCount="1" GlyphCount="1"><ofd:Glyphs>70</ofd:Glyphs></ofd:CGTransform><ofd:TextCode X="0" Y="8.6007">单</ofd:TextCode></ofd:TextObject><ofd:TextObject ID="146" CTM="0.3528 0 0 0.3528 0 0" Boundary="190.6323 46.7869 3.4086 3.5286" Font="6" Size="10.0125"><ofd:CGTransform CodePosition="0" CodeCount="1" GlyphCount="1"><ofd:Glyphs>170</ofd:Glyphs></ofd:CGTransform><ofd:TextCode X="0" Y="8.6007">︶</ofd:TextCode></ofd:TextObject><ofd:TextObject ID="147" CTM="0.3528 0 0 0.3528 0 0" Boundary="190.6323 50.3191 3.4086 3.5286" Font="6" Size="10.0125"><ofd:CGTransform CodePosition="0" CodeCount="1" GlyphCount="1"><ofd:Glyphs>169</ofd:Glyphs></ofd:CGTransform><ofd:TextCode X="0" Y="8.6007">︵</ofd:TextCode></ofd:TextObject><ofd:TextObject ID="148" CTM="0.3528 0 0 0.3528 0 0" Boundary="190.6323 53.8513 3.3944 3.5286" Font="6" Size="10.0125"><ofd:CGTransform CodePosition="0" CodeCount="1" GlyphCount="1"><ofd:Glyphs>48</ofd:Glyphs></ofd:CGTransform><ofd:TextCode X="0" Y="8.6007">付</ofd:TextCode></ofd:TextObject><ofd:TextObject ID="149" CTM="0.3528 0 0 0.3528 0 0" Boundary="190.6323 57.3835 3.3803 3.5286" Font="6" Size="10.0125"><ofd:CGTransform CodePosition="0" CodeCount="1" GlyphCount="1"><ofd:Glyphs>117</ofd:Glyphs></ofd:CGTransform><ofd:TextCode X="0" Y="8.6007">款</ofd:TextCode></ofd:TextObject><ofd:TextObject ID="150" CTM="0.3528 0 0 0.3528 0 0" Boundary="190.6323 60.9157 3.3803 3.5286" Font="6" Size="10.0125"><ofd:CGTransform CodePosition="0" CodeCount="1" GlyphCount="1"><ofd:Glyphs>47</ofd:Glyphs></ofd:CGTransform><ofd:TextCode X="0" Y="8.6007">人</ofd:TextCode></ofd:TextObject><ofd:TextObject ID="151" CTM="0.3528 0 0 0.3528 0 0" Boundary="190.6323 64.4478 3.1472 3.5286" Font="6" Size="10.0125"><ofd:CGTransform CodePosition="0" CodeCount="1" GlyphCount="1"><ofd:Glyphs>77</ofd:Glyphs></ofd:CGTransform><ofd:TextCode X="0" Y="8.6007">回</ofd:TextCode></ofd:TextObject><ofd:TextObject ID="152" CTM="0.3528 0 0 0.3528 0 0" Boundary="190.6323 67.98 3.3803 3.5286" Font="6" Size="10.0125"><ofd:CGTransform CodePosition="0" CodeCount="1" GlyphCount="1"><ofd:Glyphs>70</ofd:Glyphs></ofd:CGTransform><ofd:TextCode X="0" Y="8.6007">单</ofd:TextCode></ofd:TextObject><ofd:TextObject ID="153" CTM="0.3528 0 0 0.3528 0 0" Boundary="190.6323 71.5122 3.4086 3.5286" Font="6" Size="10.0125"><ofd:CGTransform CodePosition="0" CodeCount="1" GlyphCount="1"><ofd:Glyphs>170</ofd:Glyphs></ofd:CGTransform><ofd:TextCode X="0" Y="8.6007">︶</ofd:TextCode></ofd:TextObject><ofd:TextObject ID="154" CTM="0.3528 0 0 0.3528 0 0" Boundary="18.2298 26.3214 10.3776 3.5286" Font="6" Size="10.0125"><ofd:CGTransform CodePosition="0" CodeCount="3" GlyphCount="3"><ofd:Glyphs>149 36 74</ofd:Glyphs></ofd:CGTransform><ofd:TextCode X="0" Y="8.6007" DeltaX="10.0125 10.0125">账 号</ofd:TextCode></ofd:TextObject><ofd:TextObject ID="155" CTM="0.3528 0 0 0.3528 0 0" Boundary="32.3585 26.3214 35.1135 3.5286" Font="6" Size="10.0125"><ofd:CGTransform CodePosition="0" CodeCount="20" GlyphCount="20"><ofd:Glyphs>7 7 6 11 6 7 14 14 9 12 6 6 6 14 8 8 10 10 8 14</ofd:Glyphs></ofd:CGTransform><ofd:TextCode X="0" Y="8.6007" DeltaX="5.0062 5.0062 5.0062 5.0063 5.0063 5.0063 5.0063 5.0062 5.0062 5.0062 5.0062 5.0062 5.0063 5.0062 5.0062 5.0062 5.0062 5.0062 5.0062">11050188360008224428</ofd:TextCode></ofd:TextObject><ofd:TextObject ID="156" CTM="0.3528 0 0 0.3528 0 0" Boundary="108.4527 26.3214 10.3776 3.5286" Font="6" Size="10.0125"><ofd:CGTransform CodePosition="0" CodeCount="3" GlyphCount="3"><ofd:Glyphs>149 36 74</ofd:Glyphs></ofd:CGTransform><ofd:TextCode X="0" Y="8.6007" DeltaX="10.0125 10.0125">账 号</ofd:TextCode></ofd:TextObject><ofd:TextObject ID="157" CTM="0.3528 0 0 0.3528 0 0" Boundary="122.5815 26.3214 33.3474 3.5286" Font="6" Size="10.0125"><ofd:CGTransform CodePosition="0" CodeCount="19" GlyphCount="19"><ofd:Glyphs>12 8 7 13 6 6 6 6 7 6 7 10 7 14 8 7 14 14 13</ofd:Glyphs></ofd:CGTransform><ofd:TextCode X="0" Y="8.6007" DeltaX="5.0062 5.0062 5.0062 5.0063 5.0063 5.0063 5.0063 5.0062 5.0062 5.0062 5.0062 5.0062 5.0063 5.0062 5.0062 5.0062 5.0062 5.0062">6217000010141821887</ofd:TextCode></ofd:TextObject><ofd:TextObject ID="158" CTM="0.3528 0 0 0.3528 0 0" Boundary="18.2298 31.1765 10.4164 3.5286" Font="6" Size="10.0125"><ofd:CGTransform CodePosition="0" CodeCount="3" GlyphCount="3"><ofd:Glyphs>92 96 143</ofd:Glyphs></ofd:CGTransform><ofd:TextCode X="0" Y="8.6007" DeltaX="10.0125 10.0125">开户行</ofd:TextCode></ofd:TextObject><ofd:TextObject ID="159" CTM="0.3528 0 0 0.3528 0 0" Boundary="32.3585 31.1765 63.3992 3.5286" Font="6" Size="10.0125"><ofd:CGTransform CodePosition="0" CodeCount="18" GlyphCount="18"><ofd:Glyphs>43 78 91 145 162 143 140 50 110 164 58 75 68 46 39 79 101 143</ofd:Glyphs></ofd:CGTransform><ofd:TextCode X="0" Y="8.6007" DeltaX="10.0125 10.0125 10.0125 10.0125 10.0125 10.0125 10.0125 10.0125 10.0125 10.0125 10.0125 10.0125 10.0125 10.0125 10.0125 10.0125 10.0125">中国建设银行股份有限公司北京上地支行</ofd:TextCode></ofd:TextObject><ofd:TextObject ID="160" CTM="0.3528 0 0 0.3528 0 0" Boundary="108.4527 31.1765 10.4164 3.5286" Font="6" Size="10.0125"><ofd:CGTransform CodePosition="0" CodeCount="3" GlyphCount="3"><ofd:Glyphs>92 96 143</ofd:Glyphs></ofd:CGTransform><ofd:TextCode X="0" Y="8.6007" DeltaX="10.0125 10.0125">开户行</ofd:TextCode></ofd:TextObject><ofd:TextObject ID="161" CTM="0.3528 0 0 0.3528 0 0" Boundary="122.3169 31.4991 56.2126 2.815" Font="6" Size="7.9875"><ofd:CGTransform CodePosition="0" CodeCount="20" GlyphCount="20"><ofd:Glyphs>43 78 91 145 162 143 140 50 110 164 58 75 68 46 123 69 42 154 101 143</ofd:Glyphs></ofd:CGTransform><ofd:TextCode X="0" Y="6.8613" DeltaX="7.9875 7.9875 7.9875 7.9875 7.9875 7.9875 7.9875 7.9875 7.9875 7.9875 7.9875 7.9875 7.9875 7.9875 7.9875 7.9875 7.9875 7.9875 7.9875">中国建设银行股份有限公司北京清华东路支行</ofd:TextCode></ofd:TextObject><ofd:TextObject ID="162" CTM="0.3528 0 0 0.3528 0 0" Boundary="16.51 36.2432 6.9266 3.5286" Font="6" Size="10.0125"><ofd:CGTransform CodePosition="0" CodeCount="2" GlyphCount="2"><ofd:Glyphs>161 166</ofd:Glyphs></ofd:CGTransform><ofd:TextCode X="0" Y="8.6007" DeltaX="10.0125">金额</ofd:TextCode></ofd:TextObject><ofd:TextObject ID="163" CTM="0.3528 0 0 0.3528 0 0" Boundary="32.3585 36.2432 42.2061 3.5286" Font="6" Size="10.0125"><ofd:CGTransform CodePosition="0" CodeCount="12" GlyphCount="12"><ofd:Glyphs>171 82 60 172 47 119 89 151 99 114 56 104</ofd:Glyphs></ofd:CGTransform><ofd:TextCode X="0" Y="8.6007" DeltaX="10.0125 10.0125 10.0125 10.0125 10.0125 10.0125 10.0125 10.0125 10.0125 10.0125 10.0125">（大写）人民币贰拾柒元整</ofd:TextCode></ofd:TextObject><ofd:TextObject ID="164" CTM="0.3528 0 0 0.3528 0 0" Boundary="122.4492 36.2432 26.3113 3.5286" Font="6" Size="10.0125"><ofd:CGTransform CodePosition="0" CodeCount="10" GlyphCount="10"><ofd:Glyphs>171 88 60 172 175 8 13 5 6 6</ofd:Glyphs></ofd:CGTransform><ofd:TextCode X="0" Y="8.6007" DeltaX="10.0125 10.0125 10.0125 10.0125 10.0125 5.0062 5.0062 5.0062 5.0062">（小写）￥27.00</ofd:TextCode></ofd:TextObject><ofd:TextObject ID="165" CTM="0.3528 0 0 0.3528 0 0" Boundary="12.9778 41.3233 13.9769 3.5286" Font="6" Size="10.0125"><ofd:CGTransform CodePosition="0" CodeCount="4" GlyphCount="4"><ofd:Glyphs>62 146 130 137</ofd:Glyphs></ofd:CGTransform><ofd:TextCode X="0" Y="8.6007" DeltaX="10.0125 10.0125 10.0125">凭证种类</ofd:TextCode></ofd:TextObject><ofd:TextObject ID="166" CTM="0.3528 0 0 0.3528 0 0" Boundary="32.3585 41.3233 21.0412 3.5286" Font="6" Size="10.0125"><ofd:CGTransform CodePosition="0" CodeCount="6" GlyphCount="6"><ofd:Glyphs>126 84 156 149 62 146</ofd:Glyphs></ofd:CGTransform><ofd:TextCode X="0" Y="8.6007" DeltaX="10.0125 10.0125 10.0125 10.0125 10.0125">电子转账凭证</ofd:TextCode></ofd:TextObject><ofd:TextObject ID="167" CTM="0.3528 0 0 0.3528 0 0" Boundary="103.2007 41.3233 13.9486 3.5286" Font="6" Size="10.0125"><ofd:CGTransform CodePosition="0" CodeCount="4" GlyphCount="4"><ofd:Glyphs>62 146 74 129</ofd:Glyphs></ofd:CGTransform><ofd:TextCode X="0" Y="8.6007" DeltaX="10.0125 10.0125 10.0125">凭证号码</ofd:TextCode></ofd:TextObject><ofd:TextObject ID="168" CTM="0.3528 0 0 0.3528 0 0" Boundary="122.5815 41.3233 20.9847 3.5286" Font="6" Size="10.0125"><ofd:CGTransform CodePosition="0" CodeCount="12" GlyphCount="12"><ofd:Glyphs>11 8 7 10 13 6 9 11 13 10 9 13</ofd:Glyphs></ofd:CGTransform><ofd:TextCode X="0" Y="8.6007" DeltaX="5.0062 5.0062 5.0062 5.0063 5.0063 5.0063 5.0063 5.0062 5.0062 5.0062 5.0062">521470357437</ofd:TextCode></ofd:TextObject><ofd:TextObject ID="169" CTM="0.3528 0 0 0.3528 0 0" Boundary="12.9778 46.1784 14.0051 3.5286" Font="6" Size="10.0125"><ofd:CGTransform CodePosition="0" CodeCount="4" GlyphCount="4"><ofd:Glyphs>138 136 105 93</ofd:Glyphs></ofd:CGTransform><ofd:TextCode X="0" Y="8.6007" DeltaX="10.0125 10.0125 10.0125">结算方式</ofd:TextCode></ofd:TextObject><ofd:TextObject ID="170" CTM="0.3528 0 0 0.3528 0 0" Boundary="32.3585 46.1784 6.803 3.5286" Font="6" Size="10.0125"><ofd:CGTransform CodePosition="0" CodeCount="2" GlyphCount="2"><ofd:Glyphs>121 64</ofd:Glyphs></ofd:CGTransform><ofd:TextCode X="0" Y="8.6007" DeltaX="10.0125">汇划</ofd:TextCode></ofd:TextObject><ofd:TextObject ID="171" CTM="0.3528 0 0 0.3528 0 0" Boundary="104.9734 46.1784 10.4306 3.5286" Font="6" Size="10.0125"><ofd:CGTransform CodePosition="0" CodeCount="3" GlyphCount="3"><ofd:Glyphs>125 36 158</ofd:Glyphs></ofd:CGTransform><ofd:TextCode X="0" Y="8.6007" DeltaX="10.0125 10.0125">用 途</ofd:TextCode></ofd:TextObject><ofd:TextObject ID="172" CTM="0.3528 0 0 0.3528 0 0" Boundary="122.3169 46.5009 57.5905 2.815" Font="6" Size="7.9875"><ofd:CGTransform CodePosition="0" CodeCount="30" GlyphCount="30"><ofd:Glyphs>8 12 6 11 7 7 6 10 13 13 2 6 7 6 6 14 6 6 3 148 66 80 112 54 83 98 63 132 155 152</ofd:Glyphs></ofd:CGTransform><ofd:TextCode X="0" Y="6.8613" DeltaX="3.9938 3.9938 3.9938 3.9937 3.9937 3.9937 3.9937 3.9937 3.9937 3.9938 3.9938 3.9938 3.9938 3.9938 3.9938 3.9938 3.9938 3.9938 3.9938 7.9875 7.9875 7.9875 7.9875 7.9875 7.9875 7.9875 7.9875 7.9875 7.9875">2605110477(0100800)财务处李俊婕报出租车费</ofd:TextCode></ofd:TextObject><ofd:TextObject ID="173" CTM="0.3528 0 0 0.3528 0 0" Boundary="9.062 51.0335 52.8027 3.5286" Font="6" Size="10.0125"><ofd:CGTransform CodePosition="0" CodeCount="25" GlyphCount="25"><ofd:Glyphs>101 48 62 146 74 16 1 8 6 8 12 11 8 7 10 6 6 10 11 15 6 9 10 8 6</ofd:Glyphs></ofd:CGTransform><ofd:TextCode X="0" Y="8.6007" DeltaX="10.0125 10.0125 10.0125 10.0125 10.0125 5.0062 5.0062 5.0062 5.0062 5.0062 5.0062 5.0062 5.0062 5.0062 5.0062 5.0062 5.0062 5.0062 5.0062 5.0062 5.0062 5.0063 5.0063 5.0063">支付凭证号: 202652140045903420</ofd:TextCode></ofd:TextObject><ofd:TextObject ID="174" CTM="0.3528 0 0 0.3528 0 0" Boundary="9.062 55.0948 70.4495 3.5286" Font="6" Size="10.0125"><ofd:CGTransform CodePosition="0" CodeCount="30" GlyphCount="30"><ofd:Glyphs>165 136 70 52 16 1 7 8 7 6 6 6 6 6 10 6 6 6 7 14 7 12 8 19 43 78 61 41 82 85</ofd:Glyphs></ofd:CGTransform><ofd:TextCode X="0" Y="8.6007" DeltaX="10.0125 10.0125 10.0125 10.0125 5.0062 5.0062 5.0062 5.0062 5.0063 5.0062 5.0062 5.0062 5.0062 5.0062 5.0062 5.0062 5.0062 5.0062 5.0062 5.0062 5.0062 5.0062 5.0063 5.0063 10.0125 10.0125 10.0125 10.0125 10.0125">预算单位: 12100000400018162G中国农业大学</ofd:TextCode></ofd:TextObject><ofd:TextObject ID="175" CTM="0.3528 0 0 0.3528 0 0" Boundary="9.062 59.1562 51.0648 3.5286" Font="6" Size="10.0125"><ofd:CGTransform CodePosition="0" CodeCount="17" GlyphCount="17"><ofd:Glyphs>153 161 94 150 16 1 7 7 7 38 142 58 59 165 136 153 161</ofd:Glyphs></ofd:CGTransform><ofd:TextCode X="0" Y="8.6007" DeltaX="10.0125 10.0125 10.0125 10.0125 5.0062 5.0062 5.0062 5.0062 5.0063 10.0125 10.0125 10.0125 10.0125 10.0125 10.0125 10.0125">资金性质: 111一般公共预算资金</ofd:TextCode></ofd:TextObject><ofd:TextObject ID="176" CTM="0.3528 0 0 0.3528 0 0" Boundary="9.062 63.2175 43.8627 3.5286" Font="6" Size="10.0125"><ofd:CGTransform CodePosition="0" CodeCount="17" GlyphCount="17"><ofd:Glyphs>165 136 131 127 16 1 8 6 11 6 8 6 11 168 135 103 141</ofd:Glyphs></ofd:CGTransform><ofd:TextCode X="0" Y="8.6007" DeltaX="10.0125 10.0125 10.0125 10.0125 5.0062 5.0062 5.0062 5.0062 5.0063 5.0062 5.0062 5.0062 5.0062 10.0125 10.0125 10.0125">预算科目: 2050205高等教育</ofd:TextCode></ofd:TextObject><ofd:TextObject ID="177" CTM="0.3528 0 0 0.3528 0 0" Boundary="99.2849 51.0335 31.4294 3.5286" Font="6" Size="10.0125"><ofd:CGTransform CodePosition="0" CodeCount="13" GlyphCount="13"><ofd:Glyphs>97 72 115 76 174 30 7 27 21 24 25 6 7</ofd:Glyphs></ofd:CGTransform><ofd:TextCode X="0" Y="8.6007" DeltaX="10.0125 10.0125 10.0125 10.0125 10.0125 5.0062 5.0062 5.0062 5.0062 5.0062 5.0062 5.0062">打印柜员：Z1WLPT01</ofd:TextCode></ofd:TextObject><ofd:TextObject ID="178" CTM="0.3528 0 0 0.3528 0 0" Boundary="99.2849 55.0948 38.6739 3.5286" Font="6" Size="10.0125"><ofd:CGTransform CodePosition="0" CodeCount="11" GlyphCount="11"><ofd:Glyphs>97 72 111 113 174 43 78 91 145 162 143</ofd:Glyphs></ofd:CGTransform><ofd:TextCode X="0" Y="8.6007" DeltaX="10.0125 10.0125 10.0125 10.0125 10.0125 10.0125 10.0125 10.0125 10.0125 10.0125">打印机构：中国建设银行</ofd:TextCode></ofd:TextObject><ofd:TextObject ID="179" CTM="0.3528 0 0 0.3528 0 0" Boundary="99.2849 59.1562 15.0824 3.5286" Font="6" Size="10.0125"><ofd:CGTransform CodePosition="0" CodeCount="5" GlyphCount="5"><ofd:Glyphs>97 72 71 74 174</ofd:Glyphs></ofd:CGTransform><ofd:TextCode X="0" Y="8.6007" DeltaX="10.0125 10.0125 10.0125 10.0125">打印卡号：</ofd:TextCode></ofd:TextObject><ofd:TextObject ID="180" CTM="0.3528 0 0 0.3528 0 0" Boundary="161.9779 83.6301 33.3757 3.5286" Font="6" Size="10.0125"><ofd:CGTransform CodePosition="0" CodeCount="14" GlyphCount="14"><ofd:Glyphs>45 108 111 113 174 7 7 6 14 14 9 12 6 6</ofd:Glyphs></ofd:CGTransform><ofd:TextCode X="0" Y="8.6007" DeltaX="10.0125 10.0125 10.0125 10.0125 10.0125 5.0062 5.0063 5.0063 5.0062 5.0062 5.0062 5.0062 5.0063">交易机构：110883600</ofd:TextCode></ofd:TextObject><ofd:TextObject ID="182" CTM="0.3528 0 0 0.3528 0 0" Boundary="98.6234 83.6301 31.6096 3.5286" Font="6" Size="10.0125"><ofd:CGTransform CodePosition="0" CodeCount="13" GlyphCount="13"><ofd:Glyphs>45 108 115 76 174 30 6 7 6 14 6 8 6</ofd:Glyphs></ofd:CGTransform><ofd:TextCode X="0" Y="8.6007" DeltaX="10.0125 10.0125 10.0125 10.0125 10.0125 5.0062 5.0063 5.0063 5.0062 5.0062 5.0062 5.0062">交易柜员：Z0108020</ofd:TextCode></ofd:TextObject><ofd:TextObject ID="184" CTM="0.3528 0 0 0.3528 0 0" Boundary="8.6651 83.6301 50.9977 3.5286" Font="6" Size="10.0125"><ofd:CGTransform CodePosition="0" CodeCount="24" GlyphCount="24"><ofd:Glyphs>124 95 107 163 174 8 6 8 12 4 6 11 4 7 9 1 8 9 16 8 11 16 10 8</ofd:Glyphs></ofd:CGTransform><ofd:TextCode X="0" Y="8.6007" DeltaX="10.0125 10.0125 10.0125 10.0125 10.0125 5.0062 5.0063 5.0062 5.0063 5.0062 5.0062 5.0063 5.0062 5.0063 5.0062 5.0063 5.0062 5.0063 5.0062 5.0062 5.0062 5.0063 5.0063">生成时间：2026-05-13 23:25:42</ofd:TextCode></ofd:TextObject><ofd:ImageObject ID="187" CTM="21.9604 0 0 21.9604 0 0" Boundary="166.4891 54.6894 21.9604 21.9604" ResourceID="186"/><ofd:TextObject ID="188" CTM="0.3528 0 0 0.3528 0 0" Boundary="136.8293 17.008 47.6139 3.5286" Font="6" Size="10.0125"><ofd:CGTransform CodePosition="0" CodeCount="23" GlyphCount="23"><ofd:Glyphs>122 120 74 174 7 7 6 14 14 9 12 6 6 18 26 24 29 23 11 17 14 14 20</ofd:Glyphs></ofd:CGTransform><ofd:TextCode X="0" Y="8.6007" DeltaX="10.0125 10.0125 10.0125 10.0125 5.0062 5.0063 5.0062 5.0063 5.0062 5.0062 5.0062 5.0063 5.0062 5.0063 5.0062 5.0063 5.0062 5.0062 5.0062 5.0062 5.0062 5.0062">流水号：110883600FUPYO5A88K</ofd:TextCode></ofd:TextObject><ofd:TextObject ID="190" CTM="0.3528 0 0 0.3528 0 0" Boundary="95.8718 17.008 3.3803 3.5286" Font="6" Size="10.0125"><ofd:CGTransform CodePosition="0" CodeCount="1" GlyphCount="1"><ofd:Glyphs>90</ofd:Glyphs></ofd:CGTransform><ofd:TextCode X="0" Y="8.6007">年</ofd:TextCode></ofd:TextObject><ofd:TextObject ID="191" CTM="0.3528 0 0 0.3528 0 0" Boundary="102.9361 17.008 2.8258 3.5286" Font="6" Size="10.0125"><ofd:CGTransform CodePosition="0" CodeCount="1" GlyphCount="1"><ofd:Glyphs>109</ofd:Glyphs></ofd:CGTransform><ofd:TextCode X="0" Y="8.6007">月</ofd:TextCode></ofd:TextObject><ofd:TextObject ID="192" CTM="0.3528 0 0 0.3528 0 0" Boundary="110.0005 17.008 2.8964 3.5286" Font="6" Size="10.0125"><ofd:CGTransform CodePosition="0" CodeCount="1" GlyphCount="1"><ofd:Glyphs>106</ofd:Glyphs></ofd:CGTransform><ofd:TextCode X="0" Y="8.6007">日</ofd:TextCode></ofd:TextObject><ofd:TextObject ID="193" CTM="0.3528 0 0 0.3528 0 0" Boundary="88.8074 17.008 6.8842 3.5286" Font="6" Size="10.0125"><ofd:CGTransform CodePosition="0" CodeCount="4" GlyphCount="4"><ofd:Glyphs>8 6 8 12</ofd:Glyphs></ofd:CGTransform><ofd:TextCode X="0" Y="8.6007" DeltaX="5.0062 5.0062 5.0062">2026</ofd:TextCode></ofd:TextObject><ofd:TextObject ID="194" CTM="0.3528 0 0 0.3528 0 0" Boundary="99.404 17.008 3.3132 3.5286" Font="6" Size="10.0125"><ofd:CGTransform CodePosition="0" CodeCount="2" GlyphCount="2"><ofd:Glyphs>6 11</ofd:Glyphs></ofd:CGTransform><ofd:TextCode X="0" Y="8.6007" DeltaX="5.0062">05</ofd:TextCode></ofd:TextObject><ofd:TextObject ID="195" CTM="0.3528 0 0 0.3528 0 0" Boundary="106.4683 17.008 3.3132 3.5286" Font="6" Size="10.0125"><ofd:CGTransform CodePosition="0" CodeCount="2" GlyphCount="2"><ofd:Glyphs>7 8</ofd:Glyphs></ofd:CGTransform><ofd:TextCode X="0" Y="8.6007" DeltaX="5.0062">12</ofd:TextCode></ofd:TextObject><ofd:TextObject ID="196" CTM="0.3528 0 0 0.3528 0 0" Boundary="13.9568 17.008 20.7657 3.5286" Font="6" Size="10.0125"><ofd:CGTransform CodePosition="0" CodeCount="6" GlyphCount="6"><ofd:Glyphs>89 65 174 47 119 89</ofd:Glyphs></ofd:CGTransform><ofd:TextCode X="0" Y="8.6007" DeltaX="10.0125 10.0125 10.0125 10.0125 10.0125">币别：人民币</ofd:TextCode></ofd:TextObject><ofd:TextObject ID="198" CTM="0.3528 0 0 0.3528 0 0" Boundary="151.3814 8.8853 17.4808 3.5286" Font="6" Size="10.0125"><ofd:CGTransform CodePosition="0" CodeCount="9" GlyphCount="9"><ofd:Glyphs>22 34 174 15 10 13 14 10 12</ofd:Glyphs></ofd:CGTransform><ofd:TextCode X="0" Y="8.6007" DeltaX="5.0062 5.0062 10.0124 5.0063 5.0063 5.0062 5.0063 5.0062">No：947846</ofd:TextCode></ofd:TextObject><ofd:TextObject ID="200" CTM="0.3528 0 0 0.3528 0 0" Boundary="151.3814 12.9467 43.792 3.5286" Font="6" Size="10.0125"><ofd:CGTransform CodePosition="0" CodeCount="25" GlyphCount="25"><ofd:Glyphs>7 6 14 6 8 6 11 10 32 7 13 13 14 11 13 9 10 6 11 12 10 9 15 6 7</ofd:Glyphs></ofd:CGTransform><ofd:TextCode X="0" Y="8.6007" DeltaX="5.0062 5.0062 5.0062 5.0063 5.0063 5.0063 5.0063 5.0062 5.0062 5.0062 5.0062 5.0062 5.0063 5.0062 5.0062 5.0062 5.0062 5.0062 5.0062 5.0062 5.0062 5.0062 5.0062 5.0062">10802054c1778573405643901</ofd:TextCode></ofd:TextObject><ofd:TextObject ID="201" CTM="0.3528 0 0 0.3528 0 0" Boundary="60.8145 8.2735 73.9616 5.2864" LineWidth="0.6" Font="6" Size="15" Stroke="true"><ofd:StrokeColor Value="0 0 0"/><ofd:CGTransform CodePosition="0" CodeCount="14" GlyphCount="14"><ofd:Glyphs>43 78 91 145 162 143 70 52 87 96 40 125 77 70</ofd:Glyphs></ofd:CGTransform><ofd:TextCode X="0" Y="12.885" DeltaX="15 15 15 15 15 15 15 15 15 15 15 15 15">中国建设银行单位客户专用回单</ofd:TextCode></ofd:TextObject><ofd:ImageObject ID="203" CTM="39.3832 0 0 7.157 0 0" Boundary="8.6651 8.7445 39.3832 7.157" ResourceID="202"/></ofd:Layer></ofd:Content></ofd:Page>
